[
  {
    "id": 1,
    "name": "Aiden Markram",
    "picture": "https://i.ibb.co.com/C3cvQXGp/image.png",
    "email": "aiden.markram@example.com",
    "days_since_contact": 9,
    "status": "Active",
    "tags": ["colleague"],
    "bio": "Met during a collaborative project.",
    "goal": 9,
    "next_due_date": "2025-07-20"
  },
  {
    "id": 2,
    "name": "Pat Cummins",
    "picture": "https://i.ibb.co.com/TBKxpxSF/image.png",
    "email": "pat.cummins@example.com",
    "days_since_contact": 5,
    "status": "Strong-connection",
    "tags": ["mentor"],
    "bio": "Guided me in career growth.",
    "goal": 10,
    "next_due_date": "2025-07-18"
  },
  {
    "id": 3,
    "name": "Mustafizur Rahman",
    "picture": "https://i.ibb.co.com/R4949hm7/image.png",
    "email": "mustafizur.rahman@example.com",
    "days_since_contact": 15,
    "status": "overdue",
    "tags": ["friend", "school"],
    "bio": "Friend from school days.",
    "goal": 10,
    "next_due_date": "2025-07-15"
  },
  {
    "id": 4,
    "name": "Quinton de Kock",
    "picture": "https://i.ibb.co.com/C5RdGSNH/image.png",
    "email": "quinton.kock@example.com",
    "days_since_contact": 7,
    "status": "active",
    "tags": ["friend"],
    "bio": "Workout partner from gym.",
    "goal": 8,
    "next_due_date": "2025-07-19"
  },
  {
    "id": 5,
    "name": "David Warner",
    "picture": "https://i.ibb.co.com/vvrXC8vK/image.png",
    "email": "david.warner@example.com",
    "days_since_contact": 11,
    "status": "at-risk",
    "tags": ["friend", "college"],
    "bio": "Best friend from university.",
    "goal": 9,
    "next_due_date": "2025-07-17"
  },
  {
    "id": 6,
    "name": "Shakib Al Hasan",
    "picture": "https://i.ibb.co.com/jvDK6mP9/image.png",
    "email": "shakib.hasan@example.com",
    "days_since_contact": 6,
    "status": "active",
    "tags": ["family"],
    "bio": "Close cousin, meet often.",
    "goal": 10,
    "next_due_date": "2025-07-18"
  },
  {
    "id": 7,
    "name": "Jason Holder",
    "picture": "https://i.ibb.co.com/TxD8vxdc/image.png",
    "email": "jason.holder@example.com",
    "days_since_contact": 13,
    "status": "at-risk",
    "tags": ["partner"],
    "bio": "Business partner and collaborator.",
    "goal": 9,
    "next_due_date": "2025-07-16"
  },
  {
    "id": 8,
    "name": "Mohammad Rizwan",
    "picture": "https://i.ibb.co.com/DHZ5bw75/image.png",
    "email": "rizwan@example.com",
    "days_since_contact": 4,
    "status": "active",
    "tags": ["friend"],
    "bio": "Met through community events.",
    "goal": 9,
    "next_due_date": "2025-07-19"
  },
  {
    "id": 9,
    "name": "Jos Buttler",
    "picture": "https://i.ibb.co.com/5xch16mY/image.png",
    "email": "jos.buttler@example.com",
    "days_since_contact": 3,
    "status": "strong-connection",
    "tags": ["colleague"],
    "bio": "Teammate from previous job.",
    "goal": 10,
    "next_due_date": "2025-07-20"
  },
  {
    "id": 10,
    "name": "Shaheen Afridi",
    "picture": "https://i.ibb.co.com/N61w13VC/image.png",
    "email": "shaheen.afridi@example.com",
    "days_since_contact": 14,
    "status": "at-risk",
    "tags": ["friend", "online"],
    "bio": "Met through online platform.",
    "goal": 10,
    "next_due_date": "2025-07-15"
  },
  {
    "id": 11,
    "name": "Rahmanullah Gurbaz",
    "picture": "https://i.ibb.co.com/FRz1KMr/image.png",
    "email": "gurbaz@example.com",
    "days_since_contact": 8,
    "status": "active",
    "tags": ["friend"],
    "bio": "Connected through sports activities.",
    "goal": 8,
    "next_due_date": "2025-07-19"
  },
  {
    "id": 12,
    "name": "Steve Smith",
    "picture": "https://i.ibb.co.com/mYqYR5q/image.png",
    "email": "steve.smith@example.com",
    "days_since_contact": 2,
    "status": "strong-connection",
    "tags": ["colleague"],
    "bio": "Senior colleague and advisor.",
    "goal": 10,
    "next_due_date": "2025-07-20"
  },
  {
    "id": 13,
    "name": "Devon Conway",
    "picture": "https://i.ibb.co.com/f50kVWc/image.png",
    "email": "devon.conway@example.com",
    "days_since_contact": 9,
    "status": "recently-contacted",
    "tags": ["friend"],
    "bio": "Met during a travel trip.",
    "goal": 8,
    "next_due_date": "2025-07-18"
  },
  {
    "id": 14,
    "name": "Ben Stokes",
    "picture": "https://i.ibb.co.com/TDSCZx3y/image.png",
    "email": "ben.stokes@example.com",
    "days_since_contact": 6,
    "status": "occasional",
    "tags": ["manager"],
    "bio": "Former manager at workplace.",
    "goal": 9,
    "next_due_date": "2025-07-19"
  },
  {
    "id": 15,
    "name": "Kagiso Rabada",
    "picture": "https://i.ibb.co.com/ccVBgMxP/image.png",
    "email": "rabada@example.com",
    "days_since_contact": 12,
    "status": "at-risk",
    "tags": ["contact"],
    "bio": "Professional networking contact.",
    "goal": 9,
    "next_due_date": "2025-07-16"
  },
  {
    "id": 16,
    "name": "Tamim Iqbal",
    "picture": "https://i.ibb.co.com/PzMHQHfc/image.png",
    "email": "tamim.iqbal@example.com",
    "days_since_contact": 10,
    "status": "dormant",
    "tags": ["family"],
    "bio": "Close family member.",
    "goal": 8,
    "next_due_date": "2025-07-17"
  },
  {
    "id": 17,
    "name": "Rashid Khan",
    "picture": "https://i.ibb.co.com/svS6NVQv/image.png",
    "email": "rashid.khan@example.com",
    "days_since_contact": 1,
    "status": "strong-connection",
    "tags": ["friend"],
    "bio": "One of my closest friends.",
    "goal": 10,
    "next_due_date": "2025-07-21"
  },
  {
    "id": 18,
    "name": "Babar Azam",
    "picture": "https://i.ibb.co.com/Zp5W8LGw/image.png",
    "email": "babar.azam@example.com",
    "days_since_contact": 2,
    "status": "strong-connection",
    "tags": ["friend", "college"],
    "bio": "Friend from university.",
    "goal": 10,
    "next_due_date": "2025-07-20"
  },
  {
    "id": 19,
    "name": "Nicholas Pooran",
    "picture": "https://i.ibb.co.com/zhDPM4DS/image.png",
    "email": "pooran@example.com",
    "days_since_contact": 11,
    "status": "at-risk",
    "tags": ["friend"],
    "bio": "Met through online gaming.",
    "goal": 9,
    "next_due_date": "2025-07-17"
  },
  {
    "id": 20,
    "name": "Alzarri Joseph",
    "picture": "https://i.ibb.co.com/RrZVF02/image.png",
    "email": "joseph@example.com",
    "days_since_contact": 13,
    "status": "dormant",
    "tags": ["neighbour"],
    "bio": "Lives nearby, good relation.",
    "goal": 8,
    "next_due_date": "2025-07-16"
  },
  {
    "id": 21,
    "name": "Kane Williamson",
    "picture": "https://i.ibb.co.com/WpvP3T1S/image.png",
    "email": "williamson@example.com",
    "days_since_contact": 5,
    "status": "client-active",
    "tags": ["client"],
    "bio": "Client from previous project.",
    "goal": 9,
    "next_due_date": "2025-07-19"
  },
  {
    "id": 22,
    "name": "Trent Boult",
    "picture": "https://i.ibb.co.com/1YKcfR8b/image.png",
    "email": "boult@example.com",
    "days_since_contact": 7,
    "status": "occasional",
    "tags": ["friend"],
    "bio": "Workout accountability partner.",
    "goal": 9,
    "next_due_date": "2025-07-18"
  },
  {
    "id": 23,
    "name": "Joe Root",
    "picture": "https://i.ibb.co.com/Mk2j9t3r/image.png",
    "email": "joe.root@example.com",
    "days_since_contact": 3,
    "status": "Active",
    "tags": ["colleague"],
    "bio": "Friendly colleague at work.",
    "goal": 10,
    "next_due_date": "2025-07-20"
  },
  {
    "id": 24,
    "name": "Mohammad Nabi",
    "picture": "https://i.ibb.co.com/Ww6HNmS/image.png",
    "email": "nabi@example.com",
    "days_since_contact": 9,
    "status": "strong-connection",
    "tags": ["mentor"],
    "bio": "Respected mentor in community.",
    "goal": 8,
    "next_due_date": "2025-07-18"
  }
]
